CHANGES.txt
LICENSE.txt
README.txt
bootstrap.py
buildout.cfg
setup.py
src/s01/__init__.py
src/s01.core.egg-info/PKG-INFO
src/s01.core.egg-info/SOURCES.txt
src/s01.core.egg-info/dependency_links.txt
src/s01.core.egg-info/namespace_packages.txt
src/s01.core.egg-info/not-zip-safe
src/s01.core.egg-info/requires.txt
src/s01.core.egg-info/top_level.txt
src/s01/core/__init__.py
src/s01/core/configure.zcml
src/s01/core/interfaces.py
src/s01/core/job.py
src/s01/core/job.zcml
src/s01/core/mongo.py
src/s01/core/package.py
src/s01/core/package.zcml
src/s01/core/security.zcml
src/s01/core/tests.py
src/s01/core/util.py